LICENSE
README.md
setup.cfg
setup.py
twitternewsbot/__init__.py
twitternewsbot/__main__.py
twitternewsbot/newsfinder.py
twitternewsbot/tweeter.py
twitternewsbot/twitternewsbot.py
twitternewsbot.egg-info/PKG-INFO
twitternewsbot.egg-info/SOURCES.txt
twitternewsbot.egg-info/dependency_links.txt
twitternewsbot.egg-info/requires.txt
twitternewsbot.egg-info/top_level.txt