Metadata-Version: 2.1
Name: twitternewsbot
Version: 2.0.3
Summary: Python API allowing you to automize a personalized news delivery system.
Home-page: https://github.com/arnavmarda/twitter-news-bot/
Download-URL: https://github.com/arnavmarda/twitter-news-bot/archive/refs/tags/v2.0.3.tar.gz
Author: Arnav Marda
Author-email: arnavmarda@gmail.com
License: MIT
Keywords: AI,Twitter,News,Automation,Google News,Scraping,Requests,Tweepy,Articles
Classifier: Development Status :: 4 - Beta
Classifier: Intended Audience :: Developers
Classifier: Topic :: Software Development :: Build Tools
Classifier: License :: OSI Approved :: MIT License
Classifier: Programming Language :: Python :: 3
Classifier: Programming Language :: Python :: 3.11
License-File: LICENSE
